pyftdi_shell/__init__.py
pyftdi_shell/gpio_shell.py
pyftdi_shell/i2c_shell.py
pyftdi_shell/pyftdi_shell.py
pyftdi_shell/spi_shell.py
pyftdi_shell-0.1.2.dist-info/licenses/LICENSE
pyftdi_shell-0.1.2.dist-info/METADATA
pyftdi_shell-0.1.2.dist-info/WHEEL
pyftdi_shell-0.1.2.dist-info/entry_points.txt
pyftdi_shell-0.1.2.dist-info/top_level.txt
pyftdi_shell-0.1.2.dist-info/RECORD
