Metadata-Version: 2.4
Name: pyftdi_shell
Version: 0.1.2
Summary: Shell interface for FTDI functions (I2C/SPI/GPIO)
Author-email: Alex Fabre <m.alexfabre@gmail.com>
License:                                  Apache License
Project-URL: Homepage, https://github.com/AlexFabre/pyftdi-shell
Project-URL: Issues, https://github.com/AlexFabre/pyftdi-shell/issues
Classifier: Programming Language :: Python :: 3
Classifier: Operating System :: OS Independent
Requires-Python: >=3.10
License-File: LICENSE
Requires-Dist: pyftdi>=0.56.0
Dynamic: license-file
